tinrux/__about__.py
tinrux/__init__.py
tinrux/cli.py
tinrux/tinruxClient.py
tinrux/tinruxServer.py
tinrux/tinrux_cookies.py
tinrux-0.1.5.dist-info/METADATA
tinrux-0.1.5.dist-info/WHEEL
tinrux-0.1.5.dist-info/entry_points.txt
tinrux-0.1.5.dist-info/licenses/LICENSE.txt
tinrux-0.1.5.dist-info/RECORD
