Metadata-Version: 2.4
Name: tinrux
Version: 0.1.5
Summary: A database writed entirely on python, Tinrux is not redis
Project-URL: Documentation, https://github.com/Guille-ux/tinrux#readme
Project-URL: Issues, https://github.com/Guille-ux/tinrux/issues
Project-URL: Source, https://github.com/Guille-ux/tinrux
Author-email: Guillermo Leira Temes <guilleleiratemes@gmail.com>
License: GNU GENERAL PUBLIC LICENSE
License-File: LICENSE.txt
Classifier: Development Status :: 4 - Beta
Classifier: Programming Language :: Python
Classifier: Programming Language :: Python :: 3.8
Classifier: Programming Language :: Python :: 3.9
Classifier: Programming Language :: Python :: 3.10
Classifier: Programming Language :: Python :: 3.11
Classifier: Programming Language :: Python :: 3.12
Classifier: Programming Language :: Python :: Implementation :: CPython
Classifier: Programming Language :: Python :: Implementation :: PyPy
Requires-Python: >=3.6
